urge/__init__.py
urge/actions.py
urge/base.py
urge/utils.py
urge/procs/__init__.py
urge/procs/browser.py
urge/procs/fileoperation.py
urge/procs/memegen.py
urge/procs/weather.py
urge/procs/youdao.py
urge-0.4.7.3.dist-info/METADATA
urge-0.4.7.3.dist-info/WHEEL
urge-0.4.7.3.dist-info/top_level.txt
urge-0.4.7.3.dist-info/RECORD
